{"content":[{"businessDate":"2025-02-24","buyerBrokerName":"Premier Securities Company Ltd.","buyerMemberId":"32","contractAmount":247870,"contractId":2025022403018232,"contractQuantity":350,"contractRate":708.2,"securityName":"Multipurpose Finance Company  Limited","sellerBrokerName":"Linch Stock Market Ltd.","sellerMemberId":"41","stockId":471,"stockSymbol":"MPFL","tradeBookId":143513681,"tradeTime":"2025-02-24T14:59:46.755396"},{"businessDate":"2025-02-24","buyerBrokerName":"Nepal Stock House (PVT) Ltd.","buyerMemberId":"14","contractAmount":70840,"contractId":2025022403018231,"contractQuantity":100,"contractRate":708.4,"securityName":"Multipurpose Finance Company  Limited","sellerBrokerName":"Linch Stock Market Ltd.","sellerMemberId":"41","stockId":471,"stockSymbol":"MPFL","tradeBookId":143513680,"tradeTime":"2025-02-24T14:59:46.755371"},{"businessDate":"2025-02-24","buyerBrokerName":"Naasa Securities Co. Ltd.","buyerMemberId":"58","contractAmount":35425,"contractId":2025022403018230,"contractQuantity":50,"contractRate":708.5,"securityName":"Multipurpose Finance Company  Limited","sellerBrokerName":"Linch Stock Market Ltd.","sellerMemberId":"41","stockId":471,"stockSymbol":"MPFL","tradeBookId":143513678,"tradeTime":"2025-02-24T14:59:46.755346"},{"businessDate":"2025-02-24","buyerBrokerName":"Online Securities Pvt. Ltd.","buyerMemberId":"49","contractAmount":28344,"contractId":2025022403018229,"contractQuantity":40,"contractRate":708.6,"securityName":"Multipurpose Finance Company  Limited","sellerBrokerName":"Linch Stock Market Ltd.","sellerMemberId":"41","stockId":471,"stockSymbol":"MPFL","tradeBookId":143513676,"tradeTime":"2025-02-24T14:59:46.755314"},{"businessDate":"2025-02-24","buyerBrokerName":"Primo Securities (PVT) Ltd.","buyerMemberId":"16","contractAmount":7086,"contractId":2025022403018228,"contractQuantity":10,"contractRate":708.6,"securityName":"Multipurpose Finance Company  Limited","sellerBrokerName":"Linch Stock Market Ltd.","sellerMemberId":"41","stockId":471,"stockSymbol":"MPFL","tradeBookId":143513674,"tradeTime":"2025-02-24T14:59:46.755289"},{"businessDate":"2025-02-24","buyerBrokerName":"South Asian Bulls Pvt. Ltd.","buyerMemberId":"43","contractAmount":35435,"contractId":2025022403018227,"contractQuantity":50,"contractRate":708.7,"securityName":"Multipurpose Finance Company  Limited","sellerBrokerName":"Linch Stock Market Ltd.","sellerMemberId":"41","stockId":471,"stockSymbol":"MPFL","tradeBookId":143513672,"tradeTime":"2025-02-24T14:59:46.755244"},{"businessDate":"2025-02-24","buyerBrokerName":"Midas Stock Broking Company Private Limited","buyerMemberId":"21","contractAmount":7120,"contractId":2025022403018031,"contractQuantity":10,"contractRate":712,"securityName":"Multipurpose Finance Company  Limited","sellerBrokerName":"Dipshikha Dhitopatra Karobar Co. Pvt Ltd.","sellerMemberId":"38","stockId":471,"stockSymbol":"MPFL","tradeBookId":143511920,"tradeTime":"2025-02-24T14:59:29.593869"},{"businessDate":"2025-02-24","buyerBrokerName":"Primo Securities (PVT) Ltd.","buyerMemberId":"16","contractAmount":28344,"contractId":2025022403017963,"contractQuantity":40,"contractRate":708.6,"securityName":"Multipurpose Finance Company  Limited","sellerBrokerName":"Imperial Securities Company Pvt. Ltd.","sellerMemberId":"45","stockId":471,"stockSymbol":"MPFL","tradeBookId":143511467,"tradeTime":"2025-02-24T14:59:22.529387"},{"businessDate":"2025-02-24","buyerBrokerName":"Naasa Securities Co. Ltd.","buyerMemberId":"58","contractAmount":35425,"contractId":2025022403017727,"contractQuantity":50,"contractRate":708.5,"securityName":"Multipurpose Finance Company  Limited","sellerBrokerName":"Naasa Securities Co. Ltd.","sellerMemberId":"58","stockId":471,"stockSymbol":"MPFL","tradeBookId":143509781,"tradeTime":"2025-02-24T14:58:55.661233"},{"businessDate":"2025-02-24","buyerBrokerName":"Agrawal Securities (PVT) Ltd.","buyerMemberId":"6","contractAmount":48960,"contractId":2025022403017034,"contractQuantity":68,"contractRate":720,"securityName":"Multipurpose Finance Company  Limited","sellerBrokerName":"Premier Securities Company Ltd.","sellerMemberId":"32","stockId":471,"stockSymbol":"MPFL","tradeBookId":143503230,"tradeTime":"2025-02-24T14:55:12.037895"},{"businessDate":"2025-02-24","buyerBrokerName":"Agrawal Securities (PVT) Ltd.","buyerMemberId":"6","contractAmount":359500,"contractId":2025022403017033,"contractQuantity":500,"contractRate":719,"securityName":"Multipurpose Finance Company  Limited","sellerBrokerName":"Premier Securities Company Ltd.","sellerMemberId":"32","stockId":471,"stockSymbol":"MPFL","tradeBookId":143503227,"tradeTime":"2025-02-24T14:55:12.037866"},{"businessDate":"2025-02-24","buyerBrokerName":"Agrawal Securities (PVT) Ltd.","buyerMemberId":"6","contractAmount":286800,"contractId":2025022403017032,"contractQuantity":400,"contractRate":717,"securityName":"Multipurpose Finance Company  Limited","sellerBrokerName":"J.F. Securites (PVT) Ltd.","sellerMemberId":"7","stockId":471,"stockSymbol":"MPFL","tradeBookId":143503225,"tradeTime":"2025-02-24T14:55:12.03784"},{"businessDate":"2025-02-24","buyerBrokerName":"Agrawal Securities (PVT) Ltd.","buyerMemberId":"6","contractAmount":71500,"contractId":2025022403017031,"contractQuantity":100,"contractRate":715,"securityName":"Multipurpose Finance Company  Limited","sellerBrokerName":"Pragyan Securities (PVT) Ltd.","sellerMemberId":"10","stockId":471,"stockSymbol":"MPFL","tradeBookId":143503223,"tradeTime":"2025-02-24T14:55:12.037816"},{"businessDate":"2025-02-24","buyerBrokerName":"Agrawal Securities (PVT) Ltd.","buyerMemberId":"6","contractAmount":71500,"contractId":2025022403017030,"contractQuantity":100,"contractRate":715,"securityName":"Multipurpose Finance Company  Limited","sellerBrokerName":"Oxford Securities Pvt. Ltd.","sellerMemberId":"51","stockId":471,"stockSymbol":"MPFL","tradeBookId":143503221,"tradeTime":"2025-02-24T14:55:12.03779"},{"businessDate":"2025-02-24","buyerBrokerName":"Agrawal Securities (PVT) Ltd.","buyerMemberId":"6","contractAmount":7150,"contractId":2025022403017029,"contractQuantity":10,"contractRate":715,"securityName":"Multipurpose Finance Company  Limited","sellerBrokerName":"Naasa Securities Co. Ltd.","sellerMemberId":"58","stockId":471,"stockSymbol":"MPFL","tradeBookId":143503219,"tradeTime":"2025-02-24T14:55:12.037764"},{"businessDate":"2025-02-24","buyerBrokerName":"Agrawal Securities (PVT) Ltd.","buyerMemberId":"6","contractAmount":71200,"contractId":2025022403017028,"contractQuantity":100,"contractRate":712,"securityName":"Multipurpose Finance Company  Limited","sellerBrokerName":"Ashutosh Brokerage \u0026 Securities (PVT) Ltd.","sellerMemberId":"8","stockId":471,"stockSymbol":"MPFL","tradeBookId":143503217,"tradeTime":"2025-02-24T14:55:12.037736"},{"businessDate":"2025-02-24","buyerBrokerName":"Agrawal Securities (PVT) Ltd.","buyerMemberId":"6","contractAmount":71200,"contractId":2025022403017027,"contractQuantity":100,"contractRate":712,"securityName":"Multipurpose Finance Company  Limited","sellerBrokerName":"Sani Securities Company Ltd.","sellerMemberId":"42","stockId":471,"stockSymbol":"MPFL","tradeBookId":143503215,"tradeTime":"2025-02-24T14:55:12.037709"},{"businessDate":"2025-02-24","buyerBrokerName":"Agrawal Securities (PVT) Ltd.","buyerMemberId":"6","contractAmount":8544,"contractId":2025022403017026,"contractQuantity":12,"contractRate":712,"securityName":"Multipurpose Finance Company  Limited","sellerBrokerName":"Aryatara Investment \u0026 Securities","sellerMemberId":"57","stockId":471,"stockSymbol":"MPFL","tradeBookId":143503213,"tradeTime":"2025-02-24T14:55:12.037681"},{"businessDate":"2025-02-24","buyerBrokerName":"Agrawal Securities (PVT) Ltd.","buyerMemberId":"6","contractAmount":106575,"contractId":2025022403017025,"contractQuantity":150,"contractRate":710.5,"securityName":"Multipurpose Finance Company  Limited","sellerBrokerName":"Sani Securities Company Ltd.","sellerMemberId":"42","stockId":471,"stockSymbol":"MPFL","tradeBookId":143503211,"tradeTime":"2025-02-24T14:55:12.037649"},{"businessDate":"2025-02-24","buyerBrokerName":"Agrawal Securities (PVT) Ltd.","buyerMemberId":"6","contractAmount":131350,"contractId":2025022403017024,"contractQuantity":185,"contractRate":710,"securityName":"Multipurpose Finance Company  Limited","sellerBrokerName":"Imperial Securities Company Pvt. Ltd.","sellerMemberId":"45","stockId":471,"stockSymbol":"MPFL","tradeBookId":143503209,"tradeTime":"2025-02-24T14:55:12.037615"},{"businessDate":"2025-02-24","buyerBrokerName":"Agrawal Securities (PVT) Ltd.","buyerMemberId":"6","contractAmount":71000,"contractId":2025022403017023,"contractQuantity":100,"contractRate":710,"securityName":"Multipurpose Finance Company  Limited","sellerBrokerName":"Imperial Securities Company Pvt. Ltd.","sellerMemberId":"45","stockId":471,"stockSymbol":"MPFL","tradeBookId":143503207,"tradeTime":"2025-02-24T14:55:12.037584"},{"businessDate":"2025-02-24","buyerBrokerName":"Agrawal Securities (PVT) Ltd.","buyerMemberId":"6","contractAmount":71000,"contractId":2025022403017022,"contractQuantity":100,"contractRate":710,"securityName":"Multipurpose Finance Company  Limited","sellerBrokerName":"Pragyan Securities (PVT) Ltd.","sellerMemberId":"10","stockId":471,"stockSymbol":"MPFL","tradeBookId":143503205,"tradeTime":"2025-02-24T14:55:12.037548"},{"businessDate":"2025-02-24","buyerBrokerName":"Agrawal Securities (PVT) Ltd.","buyerMemberId":"6","contractAmount":53175,"contractId":2025022403017021,"contractQuantity":75,"contractRate":709,"securityName":"Multipurpose Finance Company  Limited","sellerBrokerName":"Sri Hari Securities Pvt. Ltd.","sellerMemberId":"56","stockId":471,"stockSymbol":"MPFL","tradeBookId":143503203,"tradeTime":"2025-02-24T14:55:12.03752"},{"businessDate":"2025-02-24","buyerBrokerName":"Agrawal Securities (PVT) Ltd.","buyerMemberId":"6","contractAmount":141680,"contractId":2025022403017020,"contractQuantity":200,"contractRate":708.4,"securityName":"Multipurpose Finance Company  Limited","sellerBrokerName":"Imperial Securities Company Pvt. Ltd.","sellerMemberId":"45","stockId":471,"stockSymbol":"MPFL","tradeBookId":143503201,"tradeTime":"2025-02-24T14:55:12.03748"},{"businessDate":"2025-02-24","buyerBrokerName":"Agrawal Securities (PVT) Ltd.","buyerMemberId":"6","contractAmount":212400,"contractId":2025022403017019,"contractQuantity":300,"contractRate":708,"securityName":"Multipurpose Finance Company  Limited","sellerBrokerName":"Thrive Brokerage House Pvt. Ltd","sellerMemberId":"13","stockId":471,"stockSymbol":"MPFL","tradeBookId":143503199,"tradeTime":"2025-02-24T14:55:12.037404"},{"businessDate":"2025-02-24","buyerBrokerName":"Investment Management Nepal Pvt. Ltd.","buyerMemberId":"53","contractAmount":7080,"contractId":2025022403016980,"contractQuantity":10,"contractRate":708,"securityName":"Multipurpose Finance Company  Limited","sellerBrokerName":"Thrive Brokerage House Pvt. Ltd","sellerMemberId":"13","stockId":471,"stockSymbol":"MPFL","tradeBookId":143502828,"tradeTime":"2025-02-24T14:54:53.593629"},{"businessDate":"2025-02-24","buyerBrokerName":"Online Securities Pvt. Ltd.","buyerMemberId":"49","contractAmount":38780.5,"contractId":2025022403016840,"contractQuantity":55,"contractRate":705.1,"securityName":"Multipurpose Finance Company  Limited","sellerBrokerName":"Kohinoor Investment \u0026 Securities Pvt. Ltd.","sellerMemberId":"35","stockId":471,"stockSymbol":"MPFL","tradeBookId":143501839,"tradeTime":"2025-02-24T14:54:09.021455"},{"businessDate":"2025-02-24","buyerBrokerName":"Opal Securities Investment (PVT) Ltd.","buyerMemberId":"4","contractAmount":7051,"contractId":2025022403016839,"contractQuantity":10,"contractRate":705.1,"securityName":"Multipurpose Finance Company  Limited","sellerBrokerName":"Kohinoor Investment \u0026 Securities Pvt. Ltd.","sellerMemberId":"35","stockId":471,"stockSymbol":"MPFL","tradeBookId":143501838,"tradeTime":"2025-02-24T14:54:09.021388"},{"businessDate":"2025-02-24","buyerBrokerName":"Cristal Kanchanjanga Securites Pvt. Ltd.","buyerMemberId":"50","contractAmount":70520,"contractId":2025022403016838,"contractQuantity":100,"contractRate":705.2,"securityName":"Multipurpose Finance Company  Limited","sellerBrokerName":"Kohinoor Investment \u0026 Securities Pvt. Ltd.","sellerMemberId":"35","stockId":471,"stockSymbol":"MPFL","tradeBookId":143501836,"tradeTime":"2025-02-24T14:54:09.021233"},{"businessDate":"2025-02-24","buyerBrokerName":"Aryatara Investment \u0026 Securities","buyerMemberId":"57","contractAmount":236912,"contractId":2025022403016799,"contractQuantity":335,"contractRate":707.2,"securityName":"Multipurpose Finance Company  Limited","sellerBrokerName":"Kohinoor Investment \u0026 Securities Pvt. Ltd.","sellerMemberId":"35","stockId":471,"stockSymbol":"MPFL","tradeBookId":143501354,"tradeTime":"2025-02-24T14:53:40.633508"},{"businessDate":"2025-02-24","buyerBrokerName":"South Asian Bulls Pvt. Ltd.","buyerMemberId":"43","contractAmount":70800,"contractId":2025022403016440,"contractQuantity":100,"contractRate":708,"securityName":"Multipurpose Finance Company  Limited","sellerBrokerName":"Thrive Brokerage House Pvt. Ltd","sellerMemberId":"13","stockId":471,"stockSymbol":"MPFL","tradeBookId":143497628,"tradeTime":"2025-02-24T14:50:23.03174"},{"businessDate":"2025-02-24","buyerBrokerName":"Dakshinkali Investment \u0026 Securities Pvt. Ltd.","buyerMemberId":"33","contractAmount":35250,"contractId":2025022403016147,"contractQuantity":50,"contractRate":705,"securityName":"Multipurpose Finance Company  Limited","sellerBrokerName":"Sani Securities Company Ltd.","sellerMemberId":"42","stockId":471,"stockSymbol":"MPFL","tradeBookId":143494641,"tradeTime":"2025-02-24T14:47:49.740211"},{"businessDate":"2025-02-24","buyerBrokerName":"Vision Securities Pvt. Ltd","buyerMemberId":"34","contractAmount":70500,"contractId":2025022403016146,"contractQuantity":100,"contractRate":705,"securityName":"Multipurpose Finance Company  Limited","sellerBrokerName":"Sani Securities Company Ltd.","sellerMemberId":"42","stockId":471,"stockSymbol":"MPFL","tradeBookId":143494640,"tradeTime":"2025-02-24T14:47:49.740145"},{"businessDate":"2025-02-24","buyerBrokerName":"J.F. Securites (PVT) Ltd.","buyerMemberId":"7","contractAmount":74025,"contractId":2025022403016145,"contractQuantity":105,"contractRate":705,"securityName":"Multipurpose Finance Company  Limited","sellerBrokerName":"Sani Securities Company Ltd.","sellerMemberId":"42","stockId":471,"stockSymbol":"MPFL","tradeBookId":143494638,"tradeTime":"2025-02-24T14:47:49.739988"},{"businessDate":"2025-02-24","buyerBrokerName":"J.F. Securites (PVT) Ltd.","buyerMemberId":"7","contractAmount":66975,"contractId":2025022403016122,"contractQuantity":95,"contractRate":705,"securityName":"Multipurpose Finance Company  Limited","sellerBrokerName":"Sajilo Broker Limited","sellerMemberId":"90","stockId":471,"stockSymbol":"MPFL","tradeBookId":143494299,"tradeTime":"2025-02-24T14:47:29.251797"},{"businessDate":"2025-02-24","buyerBrokerName":"Dipshikha Dhitopatra Karobar Co. Pvt Ltd.","buyerMemberId":"38","contractAmount":8472,"contractId":2025022403016121,"contractQuantity":12,"contractRate":706,"securityName":"Multipurpose Finance Company  Limited","sellerBrokerName":"Sajilo Broker Limited","sellerMemberId":"90","stockId":471,"stockSymbol":"MPFL","tradeBookId":143494298,"tradeTime":"2025-02-24T14:47:29.251645"},{"businessDate":"2025-02-24","buyerBrokerName":"Dipshikha Dhitopatra Karobar Co. Pvt Ltd.","buyerMemberId":"38","contractAmount":65658,"contractId":2025022403015798,"contractQuantity":93,"contractRate":706,"securityName":"Multipurpose Finance Company  Limited","sellerBrokerName":"Imperial Securities Company Pvt. Ltd.","sellerMemberId":"45","stockId":471,"stockSymbol":"MPFL","tradeBookId":143491791,"tradeTime":"2025-02-24T14:45:11.445106"},{"businessDate":"2025-02-24","buyerBrokerName":"Dipshikha Dhitopatra Karobar Co. Pvt Ltd.","buyerMemberId":"38","contractAmount":268280,"contractId":2025022403015617,"contractQuantity":380,"contractRate":706,"securityName":"Multipurpose Finance Company  Limited","sellerBrokerName":"Magnet Securities and Investment Company Private Limited","sellerMemberId":"95","stockId":471,"stockSymbol":"MPFL","tradeBookId":143489927,"tradeTime":"2025-02-24T14:43:20.199728"},{"businessDate":"2025-02-24","buyerBrokerName":"Dipshikha Dhitopatra Karobar Co. Pvt Ltd.","buyerMemberId":"38","contractAmount":17650,"contractId":2025022403015522,"contractQuantity":25,"contractRate":706,"securityName":"Multipurpose Finance Company  Limited","sellerBrokerName":"Online Securities Pvt. Ltd.","sellerMemberId":"49","stockId":471,"stockSymbol":"MPFL","tradeBookId":143489029,"tradeTime":"2025-02-24T14:42:27.622341"},{"businessDate":"2025-02-24","buyerBrokerName":"J.F. Securites (PVT) Ltd.","buyerMemberId":"7","contractAmount":17650,"contractId":2025022403015521,"contractQuantity":25,"contractRate":706,"securityName":"Multipurpose Finance Company  Limited","sellerBrokerName":"Online Securities Pvt. Ltd.","sellerMemberId":"49","stockId":471,"stockSymbol":"MPFL","tradeBookId":143489028,"tradeTime":"2025-02-24T14:42:27.622189"},{"businessDate":"2025-02-24","buyerBrokerName":"J.F. Securites (PVT) Ltd.","buyerMemberId":"7","contractAmount":134140,"contractId":2025022403015430,"contractQuantity":190,"contractRate":706,"securityName":"Multipurpose Finance Company  Limited","sellerBrokerName":"ABC Securities Private Limited","sellerMemberId":"17","stockId":471,"stockSymbol":"MPFL","tradeBookId":143488031,"tradeTime":"2025-02-24T14:41:39.307251"},{"businessDate":"2025-02-24","buyerBrokerName":"Pragyan Securities (PVT) Ltd.","buyerMemberId":"10","contractAmount":7062,"contractId":2025022403015429,"contractQuantity":10,"contractRate":706.2,"securityName":"Multipurpose Finance Company  Limited","sellerBrokerName":"ABC Securities Private Limited","sellerMemberId":"17","stockId":471,"stockSymbol":"MPFL","tradeBookId":143488030,"tradeTime":"2025-02-24T14:41:39.30719"},{"businessDate":"2025-02-24","buyerBrokerName":"Kumari Securities Private Limited","buyerMemberId":"1","contractAmount":21186,"contractId":2025022403015428,"contractQuantity":30,"contractRate":706.2,"securityName":"Multipurpose Finance Company  Limited","sellerBrokerName":"ABC Securities Private Limited","sellerMemberId":"17","stockId":471,"stockSymbol":"MPFL","tradeBookId":143488028,"tradeTime":"2025-02-24T14:41:39.307109"},{"businessDate":"2025-02-24","buyerBrokerName":"Nepal Stock House (PVT) Ltd.","buyerMemberId":"14","contractAmount":14140,"contractId":2025022403015427,"contractQuantity":20,"contractRate":707,"securityName":"Multipurpose Finance Company  Limited","sellerBrokerName":"ABC Securities Private Limited","sellerMemberId":"17","stockId":471,"stockSymbol":"MPFL","tradeBookId":143488026,"tradeTime":"2025-02-24T14:41:39.30688"},{"businessDate":"2025-02-24","buyerBrokerName":"Neev Securities Pvt. Ltd.","buyerMemberId":"47","contractAmount":70700,"contractId":2025022403015053,"contractQuantity":100,"contractRate":707,"securityName":"Multipurpose Finance Company  Limited","sellerBrokerName":"Investment Management Nepal Pvt. Ltd.","sellerMemberId":"53","stockId":471,"stockSymbol":"MPFL","tradeBookId":143484889,"tradeTime":"2025-02-24T14:39:09.307105"},{"businessDate":"2025-02-24","buyerBrokerName":"Capital Max Securities Ltd","buyerMemberId":"62","contractAmount":141400,"contractId":2025022403015052,"contractQuantity":200,"contractRate":707,"securityName":"Multipurpose Finance Company  Limited","sellerBrokerName":"Investment Management Nepal Pvt. Ltd.","sellerMemberId":"53","stockId":471,"stockSymbol":"MPFL","tradeBookId":143484888,"tradeTime":"2025-02-24T14:39:09.306833"},{"businessDate":"2025-02-24","buyerBrokerName":"Primo Securities (PVT) Ltd.","buyerMemberId":"16","contractAmount":60095,"contractId":2025022403015051,"contractQuantity":85,"contractRate":707,"securityName":"Multipurpose Finance Company  Limited","sellerBrokerName":"Investment Management Nepal Pvt. Ltd.","sellerMemberId":"53","stockId":471,"stockSymbol":"MPFL","tradeBookId":143484886,"tradeTime":"2025-02-24T14:39:09.306539"},{"businessDate":"2025-02-24","buyerBrokerName":"Primo Securities (PVT) Ltd.","buyerMemberId":"16","contractAmount":10605,"contractId":2025022403014780,"contractQuantity":15,"contractRate":707,"securityName":"Multipurpose Finance Company  Limited","sellerBrokerName":"Imperial Securities Company Pvt. Ltd.","sellerMemberId":"45","stockId":471,"stockSymbol":"MPFL","tradeBookId":143482219,"tradeTime":"2025-02-24T14:36:34.60685"},{"businessDate":"2025-02-24","buyerBrokerName":"Sani Securities Company Ltd.","buyerMemberId":"42","contractAmount":31815,"contractId":2025022403014676,"contractQuantity":45,"contractRate":707,"securityName":"Multipurpose Finance Company  Limited","sellerBrokerName":"Imperial Securities Company Pvt. Ltd.","sellerMemberId":"45","stockId":471,"stockSymbol":"MPFL","tradeBookId":143481344,"tradeTime":"2025-02-24T14:35:41.732868"},{"businessDate":"2025-02-24","buyerBrokerName":"Sani Securities Company Ltd.","buyerMemberId":"42","contractAmount":49490,"contractId":2025022403014283,"contractQuantity":70,"contractRate":707,"securityName":"Multipurpose Finance Company  Limited","sellerBrokerName":"Pragyan Securities (PVT) Ltd.","sellerMemberId":"10","stockId":471,"stockSymbol":"MPFL","tradeBookId":143478209,"tradeTime":"2025-02-24T14:32:42.720231"},{"businessDate":"2025-02-24","buyerBrokerName":"Sani Securities Company Ltd.","buyerMemberId":"42","contractAmount":241794,"contractId":2025022403014161,"contractQuantity":342,"contractRate":707,"securityName":"Multipurpose Finance Company  Limited","sellerBrokerName":"Dynamic Money Managers Securities Pvt. Ltd.","sellerMemberId":"44","stockId":471,"stockSymbol":"MPFL","tradeBookId":143476703,"tradeTime":"2025-02-24T14:30:56.710531"},{"businessDate":"2025-02-24","buyerBrokerName":"J.F. Securites (PVT) Ltd.","buyerMemberId":"7","contractAmount":111706,"contractId":2025022403014160,"contractQuantity":158,"contractRate":707,"securityName":"Multipurpose Finance Company  Limited","sellerBrokerName":"Dynamic Money Managers Securities Pvt. Ltd.","sellerMemberId":"44","stockId":471,"stockSymbol":"MPFL","tradeBookId":143476702,"tradeTime":"2025-02-24T14:30:56.710336"},{"businessDate":"2025-02-24","buyerBrokerName":"J.F. Securites (PVT) Ltd.","buyerMemberId":"7","contractAmount":63630,"contractId":2025022403013814,"contractQuantity":90,"contractRate":707,"securityName":"Multipurpose Finance Company  Limited","sellerBrokerName":"Dynamic Money Managers Securities Pvt. Ltd.","sellerMemberId":"44","stockId":471,"stockSymbol":"MPFL","tradeBookId":143474001,"tradeTime":"2025-02-24T14:27:52.563902"},{"businessDate":"2025-02-24","buyerBrokerName":"Naasa Securities Co. Ltd.","buyerMemberId":"58","contractAmount":13434.9,"contractId":2025022403013813,"contractQuantity":19,"contractRate":707.1,"securityName":"Multipurpose Finance Company  Limited","sellerBrokerName":"Dynamic Money Managers Securities Pvt. Ltd.","sellerMemberId":"44","stockId":471,"stockSymbol":"MPFL","tradeBookId":143474000,"tradeTime":"2025-02-24T14:27:52.563691"},{"businessDate":"2025-02-24","buyerBrokerName":"Sumeru Securities Pvt. Ltd.","buyerMemberId":"39","contractAmount":70800,"contractId":2025022403013812,"contractQuantity":100,"contractRate":708,"securityName":"Multipurpose Finance Company  Limited","sellerBrokerName":"Dynamic Money Managers Securities Pvt. Ltd.","sellerMemberId":"44","stockId":471,"stockSymbol":"MPFL","tradeBookId":143473998,"tradeTime":"2025-02-24T14:27:52.563512"},{"businessDate":"2025-02-24","buyerBrokerName":"J.F. Securites (PVT) Ltd.","buyerMemberId":"7","contractAmount":141600,"contractId":2025022403013811,"contractQuantity":200,"contractRate":708,"securityName":"Multipurpose Finance Company  Limited","sellerBrokerName":"Dynamic Money Managers Securities Pvt. Ltd.","sellerMemberId":"44","stockId":471,"stockSymbol":"MPFL","tradeBookId":143473996,"tradeTime":"2025-02-24T14:27:52.563337"},{"businessDate":"2025-02-24","buyerBrokerName":"Midas Stock Broking Company Private Limited","buyerMemberId":"21","contractAmount":279699.5,"contractId":2025022403013810,"contractQuantity":395,"contractRate":708.1,"securityName":"Multipurpose Finance Company  Limited","sellerBrokerName":"Dynamic Money Managers Securities Pvt. Ltd.","sellerMemberId":"44","stockId":471,"stockSymbol":"MPFL","tradeBookId":143473994,"tradeTime":"2025-02-24T14:27:52.563071"},{"businessDate":"2025-02-24","buyerBrokerName":"Trishakti Securities Public Limited","buyerMemberId":"48","contractAmount":7081,"contractId":2025022403013809,"contractQuantity":10,"contractRate":708.1,"securityName":"Multipurpose Finance Company  Limited","sellerBrokerName":"Dynamic Money Managers Securities Pvt. Ltd.","sellerMemberId":"44","stockId":471,"stockSymbol":"MPFL","tradeBookId":143473992,"tradeTime":"2025-02-24T14:27:52.562873"},{"businessDate":"2025-02-24","buyerBrokerName":"Secured Securities Ltd.","buyerMemberId":"36","contractAmount":131725.2,"contractId":2025022403013808,"contractQuantity":186,"contractRate":708.2,"securityName":"Multipurpose Finance Company  Limited","sellerBrokerName":"Dynamic Money Managers Securities Pvt. Ltd.","sellerMemberId":"44","stockId":471,"stockSymbol":"MPFL","tradeBookId":143473990,"tradeTime":"2025-02-24T14:27:52.562575"},{"businessDate":"2025-02-24","buyerBrokerName":"Secured Securities Ltd.","buyerMemberId":"36","contractAmount":9914.8,"contractId":2025022403013613,"contractQuantity":14,"contractRate":708.2,"securityName":"Multipurpose Finance Company  Limited","sellerBrokerName":"Imperial Securities Company Pvt. Ltd.","sellerMemberId":"45","stockId":471,"stockSymbol":"MPFL","tradeBookId":143472035,"tradeTime":"2025-02-24T14:25:31.478655"},{"businessDate":"2025-02-24","buyerBrokerName":"Market Securities \u0026 Exchange (PVT) Ltd.","buyerMemberId":"5","contractAmount":273365.2,"contractId":2025022403013579,"contractQuantity":386,"contractRate":708.2,"securityName":"Multipurpose Finance Company  Limited","sellerBrokerName":"Imperial Securities Company Pvt. Ltd.","sellerMemberId":"45","stockId":471,"stockSymbol":"MPFL","tradeBookId":143471496,"tradeTime":"2025-02-24T14:24:43.928252"},{"businessDate":"2025-02-24","buyerBrokerName":"Market Securities \u0026 Exchange (PVT) Ltd.","buyerMemberId":"5","contractAmount":9914.8,"contractId":2025022403013556,"contractQuantity":14,"contractRate":708.2,"securityName":"Multipurpose Finance Company  Limited","sellerBrokerName":"Cristal Kanchanjanga Securites Pvt. Ltd.","sellerMemberId":"50","stockId":471,"stockSymbol":"MPFL","tradeBookId":143471225,"tradeTime":"2025-02-24T14:24:23.163702"},{"businessDate":"2025-02-24","buyerBrokerName":"Kohinoor Investment \u0026 Securities Pvt. Ltd.","buyerMemberId":"35","contractAmount":354500,"contractId":2025022403013367,"contractQuantity":500,"contractRate":709,"securityName":"Multipurpose Finance Company  Limited","sellerBrokerName":"Sri Hari Securities Pvt. Ltd.","sellerMemberId":"56","stockId":471,"stockSymbol":"MPFL","tradeBookId":143469408,"tradeTime":"2025-02-24T14:22:14.677891"},{"businessDate":"2025-02-24","buyerBrokerName":"Nepal Investment And Securities Trading Private Limited","buyerMemberId":"19","contractAmount":17725,"contractId":2025022403013316,"contractQuantity":25,"contractRate":709,"securityName":"Multipurpose Finance Company  Limited","sellerBrokerName":"Sri Hari Securities Pvt. Ltd.","sellerMemberId":"56","stockId":471,"stockSymbol":"MPFL","tradeBookId":143468708,"tradeTime":"2025-02-24T14:21:20.303889"},{"businessDate":"2025-02-24","buyerBrokerName":"Sweta Securities Private Limited","buyerMemberId":"25","contractAmount":35445,"contractId":2025022403013251,"contractQuantity":50,"contractRate":708.9,"securityName":"Multipurpose Finance Company  Limited","sellerBrokerName":"Imperial Securities Company Pvt. Ltd.","sellerMemberId":"45","stockId":471,"stockSymbol":"MPFL","tradeBookId":143467852,"tradeTime":"2025-02-24T14:19:46.97921"},{"businessDate":"2025-02-24","buyerBrokerName":"Trishakti Securities Public Limited","buyerMemberId":"48","contractAmount":205349,"contractId":2025022403013179,"contractQuantity":290,"contractRate":708.1,"securityName":"Multipurpose Finance Company  Limited","sellerBrokerName":"Secured Securities Ltd.","sellerMemberId":"36","stockId":471,"stockSymbol":"MPFL","tradeBookId":143467025,"tradeTime":"2025-02-24T14:18:18.575432"},{"businessDate":"2025-02-24","buyerBrokerName":"Sundhara Securities Limited","buyerMemberId":"52","contractAmount":7082,"contractId":2025022403013178,"contractQuantity":10,"contractRate":708.2,"securityName":"Multipurpose Finance Company  Limited","sellerBrokerName":"Secured Securities Ltd.","sellerMemberId":"36","stockId":471,"stockSymbol":"MPFL","tradeBookId":143467024,"tradeTime":"2025-02-24T14:18:18.575292"},{"businessDate":"2025-02-24","buyerBrokerName":"Sundhara Securities Limited","buyerMemberId":"52","contractAmount":63738,"contractId":2025022403013159,"contractQuantity":90,"contractRate":708.2,"securityName":"Multipurpose Finance Company  Limited","sellerBrokerName":"Sani Securities Company Ltd.","sellerMemberId":"42","stockId":471,"stockSymbol":"MPFL","tradeBookId":143466753,"tradeTime":"2025-02-24T14:17:57.318084"},{"businessDate":"2025-02-24","buyerBrokerName":"Nepal Investment And Securities Trading Private Limited","buyerMemberId":"19","contractAmount":7082,"contractId":2025022403013158,"contractQuantity":10,"contractRate":708.2,"securityName":"Multipurpose Finance Company  Limited","sellerBrokerName":"Sani Securities Company Ltd.","sellerMemberId":"42","stockId":471,"stockSymbol":"MPFL","tradeBookId":143466752,"tradeTime":"2025-02-24T14:17:57.317874"},{"businessDate":"2025-02-24","buyerBrokerName":"Sweta Securities Private Limited","buyerMemberId":"25","contractAmount":17725,"contractId":2025022403013114,"contractQuantity":25,"contractRate":709,"securityName":"Multipurpose Finance Company  Limited","sellerBrokerName":"Sri Hari Securities Pvt. Ltd.","sellerMemberId":"56","stockId":471,"stockSymbol":"MPFL","tradeBookId":143466226,"tradeTime":"2025-02-24T14:17:02.314473"},{"businessDate":"2025-02-24","buyerBrokerName":"ABC Securities Private Limited","buyerMemberId":"17","contractAmount":70900,"contractId":2025022403012946,"contractQuantity":100,"contractRate":709,"securityName":"Multipurpose Finance Company  Limited","sellerBrokerName":"Sri Hari Securities Pvt. Ltd.","sellerMemberId":"56","stockId":471,"stockSymbol":"MPFL","tradeBookId":143464748,"tradeTime":"2025-02-24T14:14:34.652739"},{"businessDate":"2025-02-24","buyerBrokerName":"Siprabi Securities Pvt. Ltd.","buyerMemberId":"22","contractAmount":88625,"contractId":2025022403012945,"contractQuantity":125,"contractRate":709,"securityName":"Multipurpose Finance Company  Limited","sellerBrokerName":"Sri Hari Securities Pvt. Ltd.","sellerMemberId":"56","stockId":471,"stockSymbol":"MPFL","tradeBookId":143464746,"tradeTime":"2025-02-24T14:14:34.652675"},{"businessDate":"2025-02-24","buyerBrokerName":"J.F. Securites (PVT) Ltd.","buyerMemberId":"7","contractAmount":106365,"contractId":2025022403012944,"contractQuantity":150,"contractRate":709.1,"securityName":"Multipurpose Finance Company  Limited","sellerBrokerName":"Sri Hari Securities Pvt. Ltd.","sellerMemberId":"56","stockId":471,"stockSymbol":"MPFL","tradeBookId":143464744,"tradeTime":"2025-02-24T14:14:34.652527"},{"businessDate":"2025-02-24","buyerBrokerName":"J.F. Securites (PVT) Ltd.","buyerMemberId":"7","contractAmount":106365,"contractId":2025022403012909,"contractQuantity":150,"contractRate":709.1,"securityName":"Multipurpose Finance Company  Limited","sellerBrokerName":"N.M.B. SECURITIES LIMITED","sellerMemberId":"82","stockId":471,"stockSymbol":"MPFL","tradeBookId":143464483,"tradeTime":"2025-02-24T14:14:11.855621"},{"businessDate":"2025-02-24","buyerBrokerName":"Roadshow securities limited","buyerMemberId":"92","contractAmount":70950,"contractId":2025022403012901,"contractQuantity":100,"contractRate":709.5,"securityName":"Multipurpose Finance Company  Limited","sellerBrokerName":"N.M.B. SECURITIES LIMITED","sellerMemberId":"82","stockId":471,"stockSymbol":"MPFL","tradeBookId":143464305,"tradeTime":"2025-02-24T14:13:55.810829"},{"businessDate":"2025-02-24","buyerBrokerName":"Roadshow securities limited","buyerMemberId":"92","contractAmount":141900,"contractId":2025022403012875,"contractQuantity":200,"contractRate":709.5,"securityName":"Multipurpose Finance Company  Limited","sellerBrokerName":"Cristal Kanchanjanga Securites Pvt. Ltd.","sellerMemberId":"50","stockId":471,"stockSymbol":"MPFL","tradeBookId":143463997,"tradeTime":"2025-02-24T14:13:23.857363"},{"businessDate":"2025-02-24","buyerBrokerName":"Roadshow securities limited","buyerMemberId":"92","contractAmount":134805,"contractId":2025022403012728,"contractQuantity":190,"contractRate":709.5,"securityName":"Multipurpose Finance Company  Limited","sellerBrokerName":"Cristal Kanchanjanga Securites Pvt. Ltd.","sellerMemberId":"50","stockId":471,"stockSymbol":"MPFL","tradeBookId":143462497,"tradeTime":"2025-02-24T14:10:40.140982"},{"businessDate":"2025-02-24","buyerBrokerName":"Premier Securities Company Ltd.","buyerMemberId":"32","contractAmount":46117.5,"contractId":2025022403012727,"contractQuantity":65,"contractRate":709.5,"securityName":"Multipurpose Finance Company  Limited","sellerBrokerName":"Cristal Kanchanjanga Securites Pvt. Ltd.","sellerMemberId":"50","stockId":471,"stockSymbol":"MPFL","tradeBookId":143462496,"tradeTime":"2025-02-24T14:10:40.140668"},{"businessDate":"2025-02-24","buyerBrokerName":"Imperial Securities Company Pvt. Ltd.","buyerMemberId":"45","contractAmount":35600,"contractId":2025022403012559,"contractQuantity":50,"contractRate":712,"securityName":"Multipurpose Finance Company  Limited","sellerBrokerName":"Aryatara Investment \u0026 Securities","sellerMemberId":"57","stockId":471,"stockSymbol":"MPFL","tradeBookId":143460204,"tradeTime":"2025-02-24T14:07:20.972003"},{"businessDate":"2025-02-24","buyerBrokerName":"Imperial Securities Company Pvt. Ltd.","buyerMemberId":"45","contractAmount":35595,"contractId":2025022403012558,"contractQuantity":50,"contractRate":711.9,"securityName":"Multipurpose Finance Company  Limited","sellerBrokerName":"Imperial Securities Company Pvt. Ltd.","sellerMemberId":"45","stockId":471,"stockSymbol":"MPFL","tradeBookId":143460201,"tradeTime":"2025-02-24T14:07:20.971793"},{"businessDate":"2025-02-24","buyerBrokerName":"South Asian Bulls Pvt. Ltd.","buyerMemberId":"43","contractAmount":27056,"contractId":2025022403012148,"contractQuantity":38,"contractRate":712,"securityName":"Multipurpose Finance Company  Limited","sellerBrokerName":"Aryatara Investment \u0026 Securities","sellerMemberId":"57","stockId":471,"stockSymbol":"MPFL","tradeBookId":143455024,"tradeTime":"2025-02-24T13:58:59.307253"},{"businessDate":"2025-02-24","buyerBrokerName":"Capital Hub P. Ltd","buyerMemberId":"85","contractAmount":141600,"contractId":2025022403012088,"contractQuantity":200,"contractRate":708,"securityName":"Multipurpose Finance Company  Limited","sellerBrokerName":"Secured Securities Ltd.","sellerMemberId":"36","stockId":471,"stockSymbol":"MPFL","tradeBookId":143454219,"tradeTime":"2025-02-24T13:58:03.455017"},{"businessDate":"2025-02-24","buyerBrokerName":"Capital Hub P. Ltd","buyerMemberId":"85","contractAmount":70800,"contractId":2025022403011961,"contractQuantity":100,"contractRate":708,"securityName":"Multipurpose Finance Company  Limited","sellerBrokerName":"Nabil Stock Dealer Ltd.","sellerMemberId":"77","stockId":471,"stockSymbol":"MPFL","tradeBookId":143452181,"tradeTime":"2025-02-24T13:56:08.032333"},{"businessDate":"2025-02-24","buyerBrokerName":"J.F. Securites (PVT) Ltd.","buyerMemberId":"7","contractAmount":178164,"contractId":2025022403011858,"contractQuantity":252,"contractRate":707,"securityName":"Multipurpose Finance Company  Limited","sellerBrokerName":"Aryatara Investment \u0026 Securities","sellerMemberId":"57","stockId":471,"stockSymbol":"MPFL","tradeBookId":143451063,"tradeTime":"2025-02-24T13:54:27.63981"},{"businessDate":"2025-02-24","buyerBrokerName":"Creative Securities Pvt Ltd","buyerMemberId":"40","contractAmount":70700,"contractId":2025022403011857,"contractQuantity":100,"contractRate":707,"securityName":"Multipurpose Finance Company  Limited","sellerBrokerName":"Aryatara Investment \u0026 Securities","sellerMemberId":"57","stockId":471,"stockSymbol":"MPFL","tradeBookId":143451062,"tradeTime":"2025-02-24T13:54:27.639788"},{"businessDate":"2025-02-24","buyerBrokerName":"MILKY WAY SHARE BROKER COMPANY LTD ","buyerMemberId":"84","contractAmount":104754.4,"contractId":2025022403011856,"contractQuantity":148,"contractRate":707.8,"securityName":"Multipurpose Finance Company  Limited","sellerBrokerName":"Aryatara Investment \u0026 Securities","sellerMemberId":"57","stockId":471,"stockSymbol":"MPFL","tradeBookId":143451060,"tradeTime":"2025-02-24T13:54:27.639746"},{"businessDate":"2025-02-24","buyerBrokerName":"MILKY WAY SHARE BROKER COMPANY LTD ","buyerMemberId":"84","contractAmount":249145.6,"contractId":2025022403011738,"contractQuantity":352,"contractRate":707.8,"securityName":"Multipurpose Finance Company  Limited","sellerBrokerName":"Property Wiard Limited","sellerMemberId":"67","stockId":471,"stockSymbol":"MPFL","tradeBookId":143449499,"tradeTime":"2025-02-24T13:52:47.44798"},{"businessDate":"2025-02-24","buyerBrokerName":"C.B.I.L. Securities Limited","buyerMemberId":"91","contractAmount":350361,"contractId":2025022403011737,"contractQuantity":495,"contractRate":707.8,"securityName":"Multipurpose Finance Company  Limited","sellerBrokerName":"Property Wiard Limited","sellerMemberId":"67","stockId":471,"stockSymbol":"MPFL","tradeBookId":143449498,"tradeTime":"2025-02-24T13:52:47.447919"},{"businessDate":"2025-02-24","buyerBrokerName":"Dynamic Money Managers Securities Pvt. Ltd.","buyerMemberId":"44","contractAmount":37513.4,"contractId":2025022403011736,"contractQuantity":53,"contractRate":707.8,"securityName":"Multipurpose Finance Company  Limited","sellerBrokerName":"Property Wiard Limited","sellerMemberId":"67","stockId":471,"stockSymbol":"MPFL","tradeBookId":143449496,"tradeTime":"2025-02-24T13:52:47.447841"},{"businessDate":"2025-02-24","buyerBrokerName":"Sumeru Securities Pvt. Ltd.","buyerMemberId":"39","contractAmount":70800,"contractId":2025022403011735,"contractQuantity":100,"contractRate":708,"securityName":"Multipurpose Finance Company  Limited","sellerBrokerName":"Property Wiard Limited","sellerMemberId":"67","stockId":471,"stockSymbol":"MPFL","tradeBookId":143449494,"tradeTime":"2025-02-24T13:52:47.447636"},{"businessDate":"2025-02-24","buyerBrokerName":"Creative Securities Pvt Ltd","buyerMemberId":"40","contractAmount":248150,"contractId":2025022403011651,"contractQuantity":350,"contractRate":709,"securityName":"Multipurpose Finance Company  Limited","sellerBrokerName":"BHOLE GANESH SECURITIES LTD","sellerMemberId":"61","stockId":471,"stockSymbol":"MPFL","tradeBookId":143448903,"tradeTime":"2025-02-24T13:52:11.561867"},{"businessDate":"2025-02-24","buyerBrokerName":"Creative Securities Pvt Ltd","buyerMemberId":"40","contractAmount":106350,"contractId":2025022403011583,"contractQuantity":150,"contractRate":709,"securityName":"Multipurpose Finance Company  Limited","sellerBrokerName":"Online Securities Pvt. Ltd.","sellerMemberId":"49","stockId":471,"stockSymbol":"MPFL","tradeBookId":143448309,"tradeTime":"2025-02-24T13:51:30.269652"},{"businessDate":"2025-02-24","buyerBrokerName":"Aryatara Investment \u0026 Securities","buyerMemberId":"57","contractAmount":4963,"contractId":2025022403011521,"contractQuantity":7,"contractRate":709,"securityName":"Multipurpose Finance Company  Limited","sellerBrokerName":"Ashutosh Brokerage \u0026 Securities (PVT) Ltd.","sellerMemberId":"8","stockId":471,"stockSymbol":"MPFL","tradeBookId":143447977,"tradeTime":"2025-02-24T13:51:10.675993"},{"businessDate":"2025-02-24","buyerBrokerName":"Aryatara Investment \u0026 Securities","buyerMemberId":"57","contractAmount":70900,"contractId":2025022403011520,"contractQuantity":100,"contractRate":709,"securityName":"Multipurpose Finance Company  Limited","sellerBrokerName":"Neev Securities Pvt. Ltd.","sellerMemberId":"47","stockId":471,"stockSymbol":"MPFL","tradeBookId":143447975,"tradeTime":"2025-02-24T13:51:10.675842"},{"businessDate":"2025-02-24","buyerBrokerName":"Aryatara Investment \u0026 Securities","buyerMemberId":"57","contractAmount":56720,"contractId":2025022403011487,"contractQuantity":80,"contractRate":709,"securityName":"Multipurpose Finance Company  Limited","sellerBrokerName":"Naasa Securities Co. Ltd.","sellerMemberId":"58","stockId":471,"stockSymbol":"MPFL","tradeBookId":143447703,"tradeTime":"2025-02-24T13:50:56.169691"},{"businessDate":"2025-02-24","buyerBrokerName":"Aryatara Investment \u0026 Securities","buyerMemberId":"57","contractAmount":212700,"contractId":2025022403011472,"contractQuantity":300,"contractRate":709,"securityName":"Multipurpose Finance Company  Limited","sellerBrokerName":"Thrive Brokerage House Pvt. Ltd","sellerMemberId":"13","stockId":471,"stockSymbol":"MPFL","tradeBookId":143447365,"tradeTime":"2025-02-24T13:50:38.149372"},{"businessDate":"2025-02-24","buyerBrokerName":"Trishakti Securities Public Limited","buyerMemberId":"48","contractAmount":7120,"contractId":2025022403011158,"contractQuantity":10,"contractRate":712,"securityName":"Multipurpose Finance Company  Limited","sellerBrokerName":"Naasa Securities Co. Ltd.","sellerMemberId":"58","stockId":471,"stockSymbol":"MPFL","tradeBookId":143443850,"tradeTime":"2025-02-24T13:46:37.268288"},{"businessDate":"2025-02-24","buyerBrokerName":"Aryatara Investment \u0026 Securities","buyerMemberId":"57","contractAmount":53175,"contractId":2025022403011072,"contractQuantity":75,"contractRate":709,"securityName":"Multipurpose Finance Company  Limited","sellerBrokerName":"Naasa Securities Co. Ltd.","sellerMemberId":"58","stockId":471,"stockSymbol":"MPFL","tradeBookId":143442847,"tradeTime":"2025-02-24T13:45:45.32233"},{"businessDate":"2025-02-24","buyerBrokerName":"Ashutosh Brokerage \u0026 Securities (PVT) Ltd.","buyerMemberId":"8","contractAmount":71200,"contractId":2025022403010644,"contractQuantity":100,"contractRate":712,"securityName":"Multipurpose Finance Company  Limited","sellerBrokerName":"Naasa Securities Co. Ltd.","sellerMemberId":"58","stockId":471,"stockSymbol":"MPFL","tradeBookId":143439032,"tradeTime":"2025-02-24T13:41:43.802638"},{"businessDate":"2025-02-24","buyerBrokerName":"Kohinoor Investment \u0026 Securities Pvt. Ltd.","buyerMemberId":"35","contractAmount":710000,"contractId":2025022403010633,"contractQuantity":1000,"contractRate":710,"securityName":"Multipurpose Finance Company  Limited","sellerBrokerName":"Trisul Securities \u0026 Invt. Ltd.","sellerMemberId":"29","stockId":471,"stockSymbol":"MPFL","tradeBookId":143438985,"tradeTime":"2025-02-24T13:41:36.688774"},{"businessDate":"2025-02-24","buyerBrokerName":"Imperial Securities Company Pvt. Ltd.","buyerMemberId":"45","contractAmount":49059,"contractId":2025022403010632,"contractQuantity":69,"contractRate":711,"securityName":"Multipurpose Finance Company  Limited","sellerBrokerName":"Trisul Securities \u0026 Invt. Ltd.","sellerMemberId":"29","stockId":471,"stockSymbol":"MPFL","tradeBookId":143438984,"tradeTime":"2025-02-24T13:41:36.688684"},{"businessDate":"2025-02-24","buyerBrokerName":"Imperial Securities Company Pvt. Ltd.","buyerMemberId":"45","contractAmount":35550,"contractId":2025022403010475,"contractQuantity":50,"contractRate":711,"securityName":"Multipurpose Finance Company  Limited","sellerBrokerName":"Sani Securities Company Ltd.","sellerMemberId":"42","stockId":471,"stockSymbol":"MPFL","tradeBookId":143437657,"tradeTime":"2025-02-24T13:39:48.369034"},{"businessDate":"2025-02-24","buyerBrokerName":"Imperial Securities Company Pvt. Ltd.","buyerMemberId":"45","contractAmount":35550,"contractId":2025022403010236,"contractQuantity":50,"contractRate":711,"securityName":"Multipurpose Finance Company  Limited","sellerBrokerName":"Secured Securities Ltd.","sellerMemberId":"36","stockId":471,"stockSymbol":"MPFL","tradeBookId":143435017,"tradeTime":"2025-02-24T13:35:28.706661"},{"businessDate":"2025-02-24","buyerBrokerName":"Imperial Securities Company Pvt. Ltd.","buyerMemberId":"45","contractAmount":147177,"contractId":2025022403010235,"contractQuantity":207,"contractRate":711,"securityName":"Multipurpose Finance Company  Limited","sellerBrokerName":"ABC Securities Private Limited","sellerMemberId":"17","stockId":471,"stockSymbol":"MPFL","tradeBookId":143434997,"tradeTime":"2025-02-24T13:35:27.548723"},{"businessDate":"2025-02-24","buyerBrokerName":"Imperial Securities Company Pvt. Ltd.","buyerMemberId":"45","contractAmount":88164,"contractId":2025022403010081,"contractQuantity":124,"contractRate":711,"securityName":"Multipurpose Finance Company  Limited","sellerBrokerName":"ABC Securities Private Limited","sellerMemberId":"17","stockId":471,"stockSymbol":"MPFL","tradeBookId":143433033,"tradeTime":"2025-02-24T13:32:23.698853"},{"businessDate":"2025-02-24","buyerBrokerName":"Aryatara Investment \u0026 Securities","buyerMemberId":"57","contractAmount":7112,"contractId":2025022403010080,"contractQuantity":10,"contractRate":711.2,"securityName":"Multipurpose Finance Company  Limited","sellerBrokerName":"ABC Securities Private Limited","sellerMemberId":"17","stockId":471,"stockSymbol":"MPFL","tradeBookId":143433032,"tradeTime":"2025-02-24T13:32:23.698564"},{"businessDate":"2025-02-24","buyerBrokerName":"Aryatara Investment \u0026 Securities","buyerMemberId":"57","contractAmount":310542,"contractId":2025022403008846,"contractQuantity":438,"contractRate":709,"securityName":"Multipurpose Finance Company  Limited","sellerBrokerName":"Sani Securities Company Ltd.","sellerMemberId":"42","stockId":471,"stockSymbol":"MPFL","tradeBookId":143419639,"tradeTime":"2025-02-24T13:11:55.913965"},{"businessDate":"2025-02-24","buyerBrokerName":"Oxford Securities Pvt. Ltd.","buyerMemberId":"51","contractAmount":354550,"contractId":2025022403008845,"contractQuantity":500,"contractRate":709.1,"securityName":"Multipurpose Finance Company  Limited","sellerBrokerName":"Sani Securities Company Ltd.","sellerMemberId":"42","stockId":471,"stockSymbol":"MPFL","tradeBookId":143419638,"tradeTime":"2025-02-24T13:11:55.913871"},{"businessDate":"2025-02-24","buyerBrokerName":"South Asian Bulls Pvt. Ltd.","buyerMemberId":"43","contractAmount":44075.8,"contractId":2025022403008844,"contractQuantity":62,"contractRate":710.9,"securityName":"Multipurpose Finance Company  Limited","sellerBrokerName":"Sani Securities Company Ltd.","sellerMemberId":"42","stockId":471,"stockSymbol":"MPFL","tradeBookId":143419636,"tradeTime":"2025-02-24T13:11:55.9137"},{"businessDate":"2025-02-24","buyerBrokerName":"Kohinoor Investment \u0026 Securities Pvt. Ltd.","buyerMemberId":"35","contractAmount":7149,"contractId":2025022403008792,"contractQuantity":10,"contractRate":714.9,"securityName":"Multipurpose Finance Company  Limited","sellerBrokerName":"Naasa Securities Co. Ltd.","sellerMemberId":"58","stockId":471,"stockSymbol":"MPFL","tradeBookId":143418926,"tradeTime":"2025-02-24T13:10:40.863623"},{"businessDate":"2025-02-24","buyerBrokerName":"Aryatara Investment \u0026 Securities","buyerMemberId":"57","contractAmount":142380,"contractId":2025022403008711,"contractQuantity":200,"contractRate":711.9,"securityName":"Multipurpose Finance Company  Limited","sellerBrokerName":"Naasa Securities Co. Ltd.","sellerMemberId":"58","stockId":471,"stockSymbol":"MPFL","tradeBookId":143418002,"tradeTime":"2025-02-24T13:09:16.539084"},{"businessDate":"2025-02-24","buyerBrokerName":"Linch Stock Market Ltd.","buyerMemberId":"41","contractAmount":7110,"contractId":2025022403008576,"contractQuantity":10,"contractRate":711,"securityName":"Multipurpose Finance Company  Limited","sellerBrokerName":"Naasa Securities Co. Ltd.","sellerMemberId":"58","stockId":471,"stockSymbol":"MPFL","tradeBookId":143416534,"tradeTime":"2025-02-24T13:07:04.015797"},{"businessDate":"2025-02-24","buyerBrokerName":"Linch Stock Market Ltd.","buyerMemberId":"41","contractAmount":14220,"contractId":2025022403008575,"contractQuantity":20,"contractRate":711,"securityName":"Multipurpose Finance Company  Limited","sellerBrokerName":"Naasa Securities Co. Ltd.","sellerMemberId":"58","stockId":471,"stockSymbol":"MPFL","tradeBookId":143416528,"tradeTime":"2025-02-24T13:07:04.015733"},{"businessDate":"2025-02-24","buyerBrokerName":"Linch Stock Market Ltd.","buyerMemberId":"41","contractAmount":28440,"contractId":2025022403008574,"contractQuantity":40,"contractRate":711,"securityName":"Multipurpose Finance Company  Limited","sellerBrokerName":"Naasa Securities Co. Ltd.","sellerMemberId":"58","stockId":471,"stockSymbol":"MPFL","tradeBookId":143416524,"tradeTime":"2025-02-24T13:07:04.015674"},{"businessDate":"2025-02-24","buyerBrokerName":"Linch Stock Market Ltd.","buyerMemberId":"41","contractAmount":129402,"contractId":2025022403008573,"contractQuantity":182,"contractRate":711,"securityName":"Multipurpose Finance Company  Limited","sellerBrokerName":"Midas Stock Broking Company Private Limited","sellerMemberId":"21","stockId":471,"stockSymbol":"MPFL","tradeBookId":143416520,"tradeTime":"2025-02-24T13:07:04.01549"},{"businessDate":"2025-02-24","buyerBrokerName":"Aryatara Investment \u0026 Securities","buyerMemberId":"57","contractAmount":11328,"contractId":2025022403008276,"contractQuantity":16,"contractRate":708,"securityName":"Multipurpose Finance Company  Limited","sellerBrokerName":"Shree Krishna Securities Ltd.","sellerMemberId":"28","stockId":471,"stockSymbol":"MPFL","tradeBookId":143412912,"tradeTime":"2025-02-24T13:00:55.296749"},{"businessDate":"2025-02-24","buyerBrokerName":"Aryatara Investment \u0026 Securities","buyerMemberId":"57","contractAmount":283200,"contractId":2025022403008149,"contractQuantity":400,"contractRate":708,"securityName":"Multipurpose Finance Company  Limited","sellerBrokerName":"Sri Hari Securities Pvt. Ltd.","sellerMemberId":"56","stockId":471,"stockSymbol":"MPFL","tradeBookId":143411169,"tradeTime":"2025-02-24T12:58:33.657575"},{"businessDate":"2025-02-24","buyerBrokerName":"Aryatara Investment \u0026 Securities","buyerMemberId":"57","contractAmount":414180,"contractId":2025022403008096,"contractQuantity":585,"contractRate":708,"securityName":"Multipurpose Finance Company  Limited","sellerBrokerName":"Kohinoor Investment \u0026 Securities Pvt. Ltd.","sellerMemberId":"35","stockId":471,"stockSymbol":"MPFL","tradeBookId":143410689,"tradeTime":"2025-02-24T12:57:57.293578"},{"businessDate":"2025-02-24","buyerBrokerName":"Linch Stock Market Ltd.","buyerMemberId":"41","contractAmount":84972,"contractId":2025022403008095,"contractQuantity":120,"contractRate":708.1,"securityName":"Multipurpose Finance Company  Limited","sellerBrokerName":"Kohinoor Investment \u0026 Securities Pvt. Ltd.","sellerMemberId":"35","stockId":471,"stockSymbol":"MPFL","tradeBookId":143410688,"tradeTime":"2025-02-24T12:57:57.293446"},{"businessDate":"2025-02-24","buyerBrokerName":"Linch Stock Market Ltd.","buyerMemberId":"41","contractAmount":21243,"contractId":2025022403008013,"contractQuantity":30,"contractRate":708.1,"securityName":"Multipurpose Finance Company  Limited","sellerBrokerName":"Property Wiard Limited","sellerMemberId":"67","stockId":471,"stockSymbol":"MPFL","tradeBookId":143409933,"tradeTime":"2025-02-24T12:57:02.897398"},{"businessDate":"2025-02-24","buyerBrokerName":"J.F. Securites (PVT) Ltd.","buyerMemberId":"7","contractAmount":141640,"contractId":2025022403008012,"contractQuantity":200,"contractRate":708.2,"securityName":"Multipurpose Finance Company  Limited","sellerBrokerName":"Property Wiard Limited","sellerMemberId":"67","stockId":471,"stockSymbol":"MPFL","tradeBookId":143409932,"tradeTime":"2025-02-24T12:57:02.897344"},{"businessDate":"2025-02-24","buyerBrokerName":"J.F. Securites (PVT) Ltd.","buyerMemberId":"7","contractAmount":141660,"contractId":2025022403008011,"contractQuantity":200,"contractRate":708.3,"securityName":"Multipurpose Finance Company  Limited","sellerBrokerName":"Property Wiard Limited","sellerMemberId":"67","stockId":471,"stockSymbol":"MPFL","tradeBookId":143409930,"tradeTime":"2025-02-24T12:57:02.897291"},{"businessDate":"2025-02-24","buyerBrokerName":"Imperial Securities Company Pvt. Ltd.","buyerMemberId":"45","contractAmount":70830,"contractId":2025022403008010,"contractQuantity":100,"contractRate":708.3,"securityName":"Multipurpose Finance Company  Limited","sellerBrokerName":"Property Wiard Limited","sellerMemberId":"67","stockId":471,"stockSymbol":"MPFL","tradeBookId":143409928,"tradeTime":"2025-02-24T12:57:02.897238"},{"businessDate":"2025-02-24","buyerBrokerName":"Naasa Securities Co. Ltd.","buyerMemberId":"58","contractAmount":17712.5,"contractId":2025022403008009,"contractQuantity":25,"contractRate":708.5,"securityName":"Multipurpose Finance Company  Limited","sellerBrokerName":"Property Wiard Limited","sellerMemberId":"67","stockId":471,"stockSymbol":"MPFL","tradeBookId":143409926,"tradeTime":"2025-02-24T12:57:02.897168"},{"businessDate":"2025-02-24","buyerBrokerName":"Vision Securities Pvt. Ltd","buyerMemberId":"34","contractAmount":173582.5,"contractId":2025022403008008,"contractQuantity":245,"contractRate":708.5,"securityName":"Multipurpose Finance Company  Limited","sellerBrokerName":"Property Wiard Limited","sellerMemberId":"67","stockId":471,"stockSymbol":"MPFL","tradeBookId":143409924,"tradeTime":"2025-02-24T12:57:02.897091"},{"businessDate":"2025-02-24","buyerBrokerName":"Dynamic Money Managers Securities Pvt. Ltd.","buyerMemberId":"44","contractAmount":70860,"contractId":2025022403008007,"contractQuantity":100,"contractRate":708.6,"securityName":"Multipurpose Finance Company  Limited","sellerBrokerName":"Property Wiard Limited","sellerMemberId":"67","stockId":471,"stockSymbol":"MPFL","tradeBookId":143409922,"tradeTime":"2025-02-24T12:57:02.897035"},{"businessDate":"2025-02-24","buyerBrokerName":"Online Securities Pvt. Ltd.","buyerMemberId":"49","contractAmount":70860,"contractId":2025022403008006,"contractQuantity":100,"contractRate":708.6,"securityName":"Multipurpose Finance Company  Limited","sellerBrokerName":"Property Wiard Limited","sellerMemberId":"67","stockId":471,"stockSymbol":"MPFL","tradeBookId":143409920,"tradeTime":"2025-02-24T12:57:02.896882"},{"businessDate":"2025-02-24","buyerBrokerName":"Dynamic Money Managers Securities Pvt. Ltd.","buyerMemberId":"44","contractAmount":33323,"contractId":2025022403007892,"contractQuantity":47,"contractRate":709,"securityName":"Multipurpose Finance Company  Limited","sellerBrokerName":"Cristal Kanchanjanga Securites Pvt. Ltd.","sellerMemberId":"50","stockId":471,"stockSymbol":"MPFL","tradeBookId":143408492,"tradeTime":"2025-02-24T12:55:34.920028"},{"businessDate":"2025-02-24","buyerBrokerName":"Vision Securities Pvt. Ltd","buyerMemberId":"34","contractAmount":38967.5,"contractId":2025022403007818,"contractQuantity":55,"contractRate":708.5,"securityName":"Multipurpose Finance Company  Limited","sellerBrokerName":"Naasa Securities Co. Ltd.","sellerMemberId":"58","stockId":471,"stockSymbol":"MPFL","tradeBookId":143407755,"tradeTime":"2025-02-24T12:54:23.67668"},{"businessDate":"2025-02-24","buyerBrokerName":"Asian Securities Private Ltd.","buyerMemberId":"26","contractAmount":35450,"contractId":2025022403007718,"contractQuantity":50,"contractRate":709,"securityName":"Multipurpose Finance Company  Limited","sellerBrokerName":"Cristal Kanchanjanga Securites Pvt. Ltd.","sellerMemberId":"50","stockId":471,"stockSymbol":"MPFL","tradeBookId":143406748,"tradeTime":"2025-02-24T12:52:49.660522"},{"businessDate":"2025-02-24","buyerBrokerName":"Naasa Securities Co. Ltd.","buyerMemberId":"58","contractAmount":35450,"contractId":2025022403007550,"contractQuantity":50,"contractRate":709,"securityName":"Multipurpose Finance Company  Limited","sellerBrokerName":"Cristal Kanchanjanga Securites Pvt. Ltd.","sellerMemberId":"50","stockId":471,"stockSymbol":"MPFL","tradeBookId":143405282,"tradeTime":"2025-02-24T12:50:56.461946"},{"businessDate":"2025-02-24","buyerBrokerName":"Trishakti Securities Public Limited","buyerMemberId":"48","contractAmount":26942,"contractId":2025022403007467,"contractQuantity":38,"contractRate":709,"securityName":"Multipurpose Finance Company  Limited","sellerBrokerName":"Cristal Kanchanjanga Securites Pvt. Ltd.","sellerMemberId":"50","stockId":471,"stockSymbol":"MPFL","tradeBookId":143404338,"tradeTime":"2025-02-24T12:49:31.83633"},{"businessDate":"2025-02-24","buyerBrokerName":"Naasa Securities Co. Ltd.","buyerMemberId":"58","contractAmount":70900,"contractId":2025022403007445,"contractQuantity":100,"contractRate":709,"securityName":"Multipurpose Finance Company  Limited","sellerBrokerName":"Cristal Kanchanjanga Securites Pvt. Ltd.","sellerMemberId":"50","stockId":471,"stockSymbol":"MPFL","tradeBookId":143404034,"tradeTime":"2025-02-24T12:49:06.975832"},{"businessDate":"2025-02-24","buyerBrokerName":"Premier Securities Company Ltd.","buyerMemberId":"32","contractAmount":109895,"contractId":2025022403007426,"contractQuantity":155,"contractRate":709,"securityName":"Multipurpose Finance Company  Limited","sellerBrokerName":"Cristal Kanchanjanga Securites Pvt. Ltd.","sellerMemberId":"50","stockId":471,"stockSymbol":"MPFL","tradeBookId":143403734,"tradeTime":"2025-02-24T12:48:41.361031"},{"businessDate":"2025-02-24","buyerBrokerName":"Dipshikha Dhitopatra Karobar Co. Pvt Ltd.","buyerMemberId":"38","contractAmount":7090,"contractId":2025022403007398,"contractQuantity":10,"contractRate":709,"securityName":"Multipurpose Finance Company  Limited","sellerBrokerName":"Cristal Kanchanjanga Securites Pvt. Ltd.","sellerMemberId":"50","stockId":471,"stockSymbol":"MPFL","tradeBookId":143403322,"tradeTime":"2025-02-24T12:48:10.005332"},{"businessDate":"2025-02-24","buyerBrokerName":"Kumari Securities Private Limited","buyerMemberId":"1","contractAmount":35450,"contractId":2025022403007397,"contractQuantity":50,"contractRate":709,"securityName":"Multipurpose Finance Company  Limited","sellerBrokerName":"Cristal Kanchanjanga Securites Pvt. Ltd.","sellerMemberId":"50","stockId":471,"stockSymbol":"MPFL","tradeBookId":143403320,"tradeTime":"2025-02-24T12:48:10.005164"},{"businessDate":"2025-02-24","buyerBrokerName":"Sumeru Securities Pvt. Ltd.","buyerMemberId":"39","contractAmount":70900,"contractId":2025022403007312,"contractQuantity":100,"contractRate":709,"securityName":"Multipurpose Finance Company  Limited","sellerBrokerName":"ABC Securities Private Limited","sellerMemberId":"17","stockId":471,"stockSymbol":"MPFL","tradeBookId":143402379,"tradeTime":"2025-02-24T12:46:51.73059"},{"businessDate":"2025-02-24","buyerBrokerName":"Trishakti Securities Public Limited","buyerMemberId":"48","contractAmount":115020,"contractId":2025022403007288,"contractQuantity":162,"contractRate":710,"securityName":"Multipurpose Finance Company  Limited","sellerBrokerName":"Cristal Kanchanjanga Securites Pvt. Ltd.","sellerMemberId":"50","stockId":471,"stockSymbol":"MPFL","tradeBookId":143402022,"tradeTime":"2025-02-24T12:46:21.685124"},{"businessDate":"2025-02-24","buyerBrokerName":"Sumeru Securities Pvt. Ltd.","buyerMemberId":"39","contractAmount":70900,"contractId":2025022403007112,"contractQuantity":100,"contractRate":709,"securityName":"Multipurpose Finance Company  Limited","sellerBrokerName":"Kalika Securities Pvt. Ltd.","sellerMemberId":"46","stockId":471,"stockSymbol":"MPFL","tradeBookId":143400647,"tradeTime":"2025-02-24T12:44:51.794859"},{"businessDate":"2025-02-24","buyerBrokerName":"Midas Stock Broking Company Private Limited","buyerMemberId":"21","contractAmount":239980,"contractId":2025022403007002,"contractQuantity":338,"contractRate":710,"securityName":"Multipurpose Finance Company  Limited","sellerBrokerName":"Cristal Kanchanjanga Securites Pvt. Ltd.","sellerMemberId":"50","stockId":471,"stockSymbol":"MPFL","tradeBookId":143399416,"tradeTime":"2025-02-24T12:43:24.621924"},{"businessDate":"2025-02-24","buyerBrokerName":"Primo Securities (PVT) Ltd.","buyerMemberId":"16","contractAmount":71100,"contractId":2025022403006823,"contractQuantity":100,"contractRate":711,"securityName":"Multipurpose Finance Company  Limited","sellerBrokerName":"Midas Stock Broking Company Private Limited","sellerMemberId":"21","stockId":471,"stockSymbol":"MPFL","tradeBookId":143397584,"tradeTime":"2025-02-24T12:40:54.996977"},{"businessDate":"2025-02-24","buyerBrokerName":"Sweta Securities Private Limited","buyerMemberId":"25","contractAmount":71100,"contractId":2025022403006804,"contractQuantity":100,"contractRate":711,"securityName":"Multipurpose Finance Company  Limited","sellerBrokerName":"Midas Stock Broking Company Private Limited","sellerMemberId":"21","stockId":471,"stockSymbol":"MPFL","tradeBookId":143397070,"tradeTime":"2025-02-24T12:40:22.777482"},{"businessDate":"2025-02-24","buyerBrokerName":"Midas Stock Broking Company Private Limited","buyerMemberId":"21","contractAmount":111470,"contractId":2025022403006574,"contractQuantity":157,"contractRate":710,"securityName":"Multipurpose Finance Company  Limited","sellerBrokerName":"Dipshikha Dhitopatra Karobar Co. Pvt Ltd.","sellerMemberId":"38","stockId":471,"stockSymbol":"MPFL","tradeBookId":143393859,"tradeTime":"2025-02-24T12:37:20.517455"},{"businessDate":"2025-02-24","buyerBrokerName":"Sani Securities Company Ltd.","buyerMemberId":"42","contractAmount":101530,"contractId":2025022403006573,"contractQuantity":143,"contractRate":710,"securityName":"Multipurpose Finance Company  Limited","sellerBrokerName":"Dipshikha Dhitopatra Karobar Co. Pvt Ltd.","sellerMemberId":"38","stockId":471,"stockSymbol":"MPFL","tradeBookId":143393858,"tradeTime":"2025-02-24T12:37:20.517299"},{"businessDate":"2025-02-24","buyerBrokerName":"South Asian Bulls Pvt. Ltd.","buyerMemberId":"43","contractAmount":71010,"contractId":2025022403006572,"contractQuantity":100,"contractRate":710.1,"securityName":"Multipurpose Finance Company  Limited","sellerBrokerName":"Dipshikha Dhitopatra Karobar Co. Pvt Ltd.","sellerMemberId":"38","stockId":471,"stockSymbol":"MPFL","tradeBookId":143393856,"tradeTime":"2025-02-24T12:37:20.517133"},{"businessDate":"2025-02-24","buyerBrokerName":"Hatemalo Financial Services Private Limited","buyerMemberId":"72","contractAmount":71010,"contractId":2025022403006571,"contractQuantity":100,"contractRate":710.1,"securityName":"Multipurpose Finance Company  Limited","sellerBrokerName":"Dipshikha Dhitopatra Karobar Co. Pvt Ltd.","sellerMemberId":"38","stockId":471,"stockSymbol":"MPFL","tradeBookId":143393854,"tradeTime":"2025-02-24T12:37:20.516811"},{"businessDate":"2025-02-24","buyerBrokerName":"Sani Securities Company Ltd.","buyerMemberId":"42","contractAmount":75970,"contractId":2025022403006123,"contractQuantity":107,"contractRate":710,"securityName":"Multipurpose Finance Company  Limited","sellerBrokerName":"Dipshikha Dhitopatra Karobar Co. Pvt Ltd.","sellerMemberId":"38","stockId":471,"stockSymbol":"MPFL","tradeBookId":143385487,"tradeTime":"2025-02-24T12:29:06.236549"},{"businessDate":"2025-02-24","buyerBrokerName":"Kumari Securities Private Limited","buyerMemberId":"1","contractAmount":71000,"contractId":2025022403006122,"contractQuantity":100,"contractRate":710,"securityName":"Multipurpose Finance Company  Limited","sellerBrokerName":"Dipshikha Dhitopatra Karobar Co. Pvt Ltd.","sellerMemberId":"38","stockId":471,"stockSymbol":"MPFL","tradeBookId":143385486,"tradeTime":"2025-02-24T12:29:06.236503"},{"businessDate":"2025-02-24","buyerBrokerName":"Kumari Securities Private Limited","buyerMemberId":"1","contractAmount":71000,"contractId":2025022403006121,"contractQuantity":100,"contractRate":710,"securityName":"Multipurpose Finance Company  Limited","sellerBrokerName":"Dipshikha Dhitopatra Karobar Co. Pvt Ltd.","sellerMemberId":"38","stockId":471,"stockSymbol":"MPFL","tradeBookId":143385484,"tradeTime":"2025-02-24T12:29:06.236455"},{"businessDate":"2025-02-24","buyerBrokerName":"Online Securities Pvt. Ltd.","buyerMemberId":"49","contractAmount":35505,"contractId":2025022403006120,"contractQuantity":50,"contractRate":710.1,"securityName":"Multipurpose Finance Company  Limited","sellerBrokerName":"Dipshikha Dhitopatra Karobar Co. Pvt Ltd.","sellerMemberId":"38","stockId":471,"stockSymbol":"MPFL","tradeBookId":143385482,"tradeTime":"2025-02-24T12:29:06.236408"},{"businessDate":"2025-02-24","buyerBrokerName":"Investment Management Nepal Pvt. Ltd.","buyerMemberId":"53","contractAmount":28408,"contractId":2025022403006119,"contractQuantity":40,"contractRate":710.2,"securityName":"Multipurpose Finance Company  Limited","sellerBrokerName":"Dipshikha Dhitopatra Karobar Co. Pvt Ltd.","sellerMemberId":"38","stockId":471,"stockSymbol":"MPFL","tradeBookId":143385480,"tradeTime":"2025-02-24T12:29:06.236357"},{"businessDate":"2025-02-24","buyerBrokerName":"Primo Securities (PVT) Ltd.","buyerMemberId":"16","contractAmount":35515,"contractId":2025022403006118,"contractQuantity":50,"contractRate":710.3,"securityName":"Multipurpose Finance Company  Limited","sellerBrokerName":"Dipshikha Dhitopatra Karobar Co. Pvt Ltd.","sellerMemberId":"38","stockId":471,"stockSymbol":"MPFL","tradeBookId":143385477,"tradeTime":"2025-02-24T12:29:06.236306"},{"businessDate":"2025-02-24","buyerBrokerName":"Dynamic Money Managers Securities Pvt. Ltd.","buyerMemberId":"44","contractAmount":30547.2,"contractId":2025022403006117,"contractQuantity":43,"contractRate":710.4,"securityName":"Multipurpose Finance Company  Limited","sellerBrokerName":"Dipshikha Dhitopatra Karobar Co. Pvt Ltd.","sellerMemberId":"38","stockId":471,"stockSymbol":"MPFL","tradeBookId":143385474,"tradeTime":"2025-02-24T12:29:06.236149"},{"businessDate":"2025-02-24","buyerBrokerName":"Dynamic Money Managers Securities Pvt. Ltd.","buyerMemberId":"44","contractAmount":40492.8,"contractId":2025022403006039,"contractQuantity":57,"contractRate":710.4,"securityName":"Multipurpose Finance Company  Limited","sellerBrokerName":"Kohinoor Investment \u0026 Securities Pvt. Ltd.","sellerMemberId":"35","stockId":471,"stockSymbol":"MPFL","tradeBookId":143384625,"tradeTime":"2025-02-24T12:28:09.963295"},{"businessDate":"2025-02-24","buyerBrokerName":"Online Securities Pvt. Ltd.","buyerMemberId":"49","contractAmount":7105,"contractId":2025022403006038,"contractQuantity":10,"contractRate":710.5,"securityName":"Multipurpose Finance Company  Limited","sellerBrokerName":"Kohinoor Investment \u0026 Securities Pvt. Ltd.","sellerMemberId":"35","stockId":471,"stockSymbol":"MPFL","tradeBookId":143384624,"tradeTime":"2025-02-24T12:28:09.963241"},{"businessDate":"2025-02-24","buyerBrokerName":"Online Securities Pvt. Ltd.","buyerMemberId":"49","contractAmount":9237.8,"contractId":2025022403006037,"contractQuantity":13,"contractRate":710.6,"securityName":"Multipurpose Finance Company  Limited","sellerBrokerName":"Kohinoor Investment \u0026 Securities Pvt. Ltd.","sellerMemberId":"35","stockId":471,"stockSymbol":"MPFL","tradeBookId":143384622,"tradeTime":"2025-02-24T12:28:09.96319"},{"businessDate":"2025-02-24","buyerBrokerName":"Dynamic Money Managers Securities Pvt. Ltd.","buyerMemberId":"44","contractAmount":14214,"contractId":2025022403006036,"contractQuantity":20,"contractRate":710.7,"securityName":"Multipurpose Finance Company  Limited","sellerBrokerName":"Kohinoor Investment \u0026 Securities Pvt. Ltd.","sellerMemberId":"35","stockId":471,"stockSymbol":"MPFL","tradeBookId":143384620,"tradeTime":"2025-02-24T12:28:09.963056"},{"businessDate":"2025-02-24","buyerBrokerName":"Sani Securities Company Ltd.","buyerMemberId":"42","contractAmount":55770,"contractId":2025022403005549,"contractQuantity":78,"contractRate":715,"securityName":"Multipurpose Finance Company  Limited","sellerBrokerName":"ABC Securities Private Limited","sellerMemberId":"17","stockId":471,"stockSymbol":"MPFL","tradeBookId":143379606,"tradeTime":"2025-02-24T12:21:54.247924"},{"businessDate":"2025-02-24","buyerBrokerName":"Sani Securities Company Ltd.","buyerMemberId":"42","contractAmount":7190,"contractId":2025022403004743,"contractQuantity":10,"contractRate":719,"securityName":"Multipurpose Finance Company  Limited","sellerBrokerName":"Dipshikha Dhitopatra Karobar Co. Pvt Ltd.","sellerMemberId":"38","stockId":471,"stockSymbol":"MPFL","tradeBookId":143371400,"tradeTime":"2025-02-24T12:12:52.300431"},{"businessDate":"2025-02-24","buyerBrokerName":"Online Securities Pvt. Ltd.","buyerMemberId":"49","contractAmount":57584,"contractId":2025022403004579,"contractQuantity":80,"contractRate":719.8,"securityName":"Multipurpose Finance Company  Limited","sellerBrokerName":"Neev Securities Pvt. Ltd.","sellerMemberId":"47","stockId":471,"stockSymbol":"MPFL","tradeBookId":143369028,"tradeTime":"2025-02-24T12:10:25.724424"},{"businessDate":"2025-02-24","buyerBrokerName":"Market Securities \u0026 Exchange (PVT) Ltd.","buyerMemberId":"5","contractAmount":21585,"contractId":2025022403003681,"contractQuantity":30,"contractRate":719.5,"securityName":"Multipurpose Finance Company  Limited","sellerBrokerName":"Siprabi Securities Pvt. Ltd.","sellerMemberId":"22","stockId":471,"stockSymbol":"MPFL","tradeBookId":143357244,"tradeTime":"2025-02-24T11:56:34.194491"},{"businessDate":"2025-02-24","buyerBrokerName":"MILKY WAY SHARE BROKER COMPANY LTD ","buyerMemberId":"84","contractAmount":7200,"contractId":2025022403003239,"contractQuantity":10,"contractRate":720,"securityName":"Multipurpose Finance Company  Limited","sellerBrokerName":"K.B.L. Securities Limited ","sellerMemberId":"94","stockId":471,"stockSymbol":"MPFL","tradeBookId":143351888,"tradeTime":"2025-02-24T11:49:47.522801"},{"businessDate":"2025-02-24","buyerBrokerName":"Online Securities Pvt. Ltd.","buyerMemberId":"49","contractAmount":70900,"contractId":2025022403003179,"contractQuantity":100,"contractRate":709,"securityName":"Multipurpose Finance Company  Limited","sellerBrokerName":"Bhrikuti Stock Broking Co. Pvt. Ltd.","sellerMemberId":"55","stockId":471,"stockSymbol":"MPFL","tradeBookId":143351123,"tradeTime":"2025-02-24T11:48:55.402976"},{"businessDate":"2025-02-24","buyerBrokerName":"Imperial Securities Company Pvt. Ltd.","buyerMemberId":"45","contractAmount":35450,"contractId":2025022403003178,"contractQuantity":50,"contractRate":709,"securityName":"Multipurpose Finance Company  Limited","sellerBrokerName":"Bhrikuti Stock Broking Co. Pvt. Ltd.","sellerMemberId":"55","stockId":471,"stockSymbol":"MPFL","tradeBookId":143351122,"tradeTime":"2025-02-24T11:48:55.402881"},{"businessDate":"2025-02-24","buyerBrokerName":"MILKY WAY SHARE BROKER COMPANY LTD ","buyerMemberId":"84","contractAmount":7218,"contractId":2025022403003177,"contractQuantity":10,"contractRate":721.8,"securityName":"Multipurpose Finance Company  Limited","sellerBrokerName":"Siprabi Securities Pvt. Ltd.","sellerMemberId":"22","stockId":471,"stockSymbol":"MPFL","tradeBookId":143351108,"tradeTime":"2025-02-24T11:48:54.397294"},{"businessDate":"2025-02-24","buyerBrokerName":"Linch Stock Market Ltd.","buyerMemberId":"41","contractAmount":106215,"contractId":2025022403002970,"contractQuantity":150,"contractRate":708.1,"securityName":"Multipurpose Finance Company  Limited","sellerBrokerName":"Premier Securities Company Ltd.","sellerMemberId":"32","stockId":471,"stockSymbol":"MPFL","tradeBookId":143348593,"tradeTime":"2025-02-24T11:45:54.386551"},{"businessDate":"2025-02-24","buyerBrokerName":"Vision Securities Pvt. Ltd","buyerMemberId":"34","contractAmount":269633.7,"contractId":2025022403002744,"contractQuantity":381,"contractRate":707.7,"securityName":"Multipurpose Finance Company  Limited","sellerBrokerName":"Arun Securities (PVT) Ltd.","sellerMemberId":"3","stockId":471,"stockSymbol":"MPFL","tradeBookId":143345939,"tradeTime":"2025-02-24T11:42:44.136944"},{"businessDate":"2025-02-24","buyerBrokerName":"Aryatara Investment \u0026 Securities","buyerMemberId":"57","contractAmount":42600,"contractId":2025022403002743,"contractQuantity":60,"contractRate":710,"securityName":"Multipurpose Finance Company  Limited","sellerBrokerName":"Arun Securities (PVT) Ltd.","sellerMemberId":"3","stockId":471,"stockSymbol":"MPFL","tradeBookId":143345938,"tradeTime":"2025-02-24T11:42:44.136918"},{"businessDate":"2025-02-24","buyerBrokerName":"Malla \u0026 Malla Stock Broking Company Pvt. Limited","buyerMemberId":"11","contractAmount":71160,"contractId":2025022403002742,"contractQuantity":100,"contractRate":711.6,"securityName":"Multipurpose Finance Company  Limited","sellerBrokerName":"Arun Securities (PVT) Ltd.","sellerMemberId":"3","stockId":471,"stockSymbol":"MPFL","tradeBookId":143345936,"tradeTime":"2025-02-24T11:42:44.136894"},{"businessDate":"2025-02-24","buyerBrokerName":"Sani Securities Company Ltd.","buyerMemberId":"42","contractAmount":15664,"contractId":2025022403002741,"contractQuantity":22,"contractRate":712,"securityName":"Multipurpose Finance Company  Limited","sellerBrokerName":"Arun Securities (PVT) Ltd.","sellerMemberId":"3","stockId":471,"stockSymbol":"MPFL","tradeBookId":143345934,"tradeTime":"2025-02-24T11:42:44.136872"},{"businessDate":"2025-02-24","buyerBrokerName":"Naasa Securities Co. Ltd.","buyerMemberId":"58","contractAmount":12104,"contractId":2025022403002740,"contractQuantity":17,"contractRate":712,"securityName":"Multipurpose Finance Company  Limited","sellerBrokerName":"Arun Securities (PVT) Ltd.","sellerMemberId":"3","stockId":471,"stockSymbol":"MPFL","tradeBookId":143345932,"tradeTime":"2025-02-24T11:42:44.136849"},{"businessDate":"2025-02-24","buyerBrokerName":"Trishakti Securities Public Limited","buyerMemberId":"48","contractAmount":35600,"contractId":2025022403002739,"contractQuantity":50,"contractRate":712,"securityName":"Multipurpose Finance Company  Limited","sellerBrokerName":"Arun Securities (PVT) Ltd.","sellerMemberId":"3","stockId":471,"stockSymbol":"MPFL","tradeBookId":143345930,"tradeTime":"2025-02-24T11:42:44.136825"},{"businessDate":"2025-02-24","buyerBrokerName":"Thrive Brokerage House Pvt. Ltd","buyerMemberId":"13","contractAmount":14260,"contractId":2025022403002738,"contractQuantity":20,"contractRate":713,"securityName":"Multipurpose Finance Company  Limited","sellerBrokerName":"Arun Securities (PVT) Ltd.","sellerMemberId":"3","stockId":471,"stockSymbol":"MPFL","tradeBookId":143345928,"tradeTime":"2025-02-24T11:42:44.136797"},{"businessDate":"2025-02-24","buyerBrokerName":"Naasa Securities Co. Ltd.","buyerMemberId":"58","contractAmount":35680,"contractId":2025022403002737,"contractQuantity":50,"contractRate":713.6,"securityName":"Multipurpose Finance Company  Limited","sellerBrokerName":"Arun Securities (PVT) Ltd.","sellerMemberId":"3","stockId":471,"stockSymbol":"MPFL","tradeBookId":143345926,"tradeTime":"2025-02-24T11:42:44.136772"},{"businessDate":"2025-02-24","buyerBrokerName":"Investment Management Nepal Pvt. Ltd.","buyerMemberId":"53","contractAmount":89300,"contractId":2025022403002736,"contractQuantity":125,"contractRate":714.4,"securityName":"Multipurpose Finance Company  Limited","sellerBrokerName":"Arun Securities (PVT) Ltd.","sellerMemberId":"3","stockId":471,"stockSymbol":"MPFL","tradeBookId":143345924,"tradeTime":"2025-02-24T11:42:44.136748"},{"businessDate":"2025-02-24","buyerBrokerName":"Investment Management Nepal Pvt. Ltd.","buyerMemberId":"53","contractAmount":142900,"contractId":2025022403002735,"contractQuantity":200,"contractRate":714.5,"securityName":"Multipurpose Finance Company  Limited","sellerBrokerName":"Arun Securities (PVT) Ltd.","sellerMemberId":"3","stockId":471,"stockSymbol":"MPFL","tradeBookId":143345922,"tradeTime":"2025-02-24T11:42:44.136724"},{"businessDate":"2025-02-24","buyerBrokerName":"Vision Securities Pvt. Ltd","buyerMemberId":"34","contractAmount":142920,"contractId":2025022403002734,"contractQuantity":200,"contractRate":714.6,"securityName":"Multipurpose Finance Company  Limited","sellerBrokerName":"Arun Securities (PVT) Ltd.","sellerMemberId":"3","stockId":471,"stockSymbol":"MPFL","tradeBookId":143345920,"tradeTime":"2025-02-24T11:42:44.136699"},{"businessDate":"2025-02-24","buyerBrokerName":"Sani Securities Company Ltd.","buyerMemberId":"42","contractAmount":100100,"contractId":2025022403002733,"contractQuantity":140,"contractRate":715,"securityName":"Multipurpose Finance Company  Limited","sellerBrokerName":"Arun Securities (PVT) Ltd.","sellerMemberId":"3","stockId":471,"stockSymbol":"MPFL","tradeBookId":143345918,"tradeTime":"2025-02-24T11:42:44.136669"},{"businessDate":"2025-02-24","buyerBrokerName":"Kumari Securities Private Limited","buyerMemberId":"1","contractAmount":214500,"contractId":2025022403002732,"contractQuantity":300,"contractRate":715,"securityName":"Multipurpose Finance Company  Limited","sellerBrokerName":"Arun Securities (PVT) Ltd.","sellerMemberId":"3","stockId":471,"stockSymbol":"MPFL","tradeBookId":143345916,"tradeTime":"2025-02-24T11:42:44.136628"},{"businessDate":"2025-02-24","buyerBrokerName":"Online Securities Pvt. Ltd.","buyerMemberId":"49","contractAmount":71500,"contractId":2025022403002731,"contractQuantity":100,"contractRate":715,"securityName":"Multipurpose Finance Company  Limited","sellerBrokerName":"Arun Securities (PVT) Ltd.","sellerMemberId":"3","stockId":471,"stockSymbol":"MPFL","tradeBookId":143345914,"tradeTime":"2025-02-24T11:42:44.136601"},{"businessDate":"2025-02-24","buyerBrokerName":"Indira securities pvt. ltd","buyerMemberId":"80","contractAmount":71700,"contractId":2025022403002730,"contractQuantity":100,"contractRate":717,"securityName":"Multipurpose Finance Company  Limited","sellerBrokerName":"Arun Securities (PVT) Ltd.","sellerMemberId":"3","stockId":471,"stockSymbol":"MPFL","tradeBookId":143345912,"tradeTime":"2025-02-24T11:42:44.136572"},{"businessDate":"2025-02-24","buyerBrokerName":"Sani Securities Company Ltd.","buyerMemberId":"42","contractAmount":25130,"contractId":2025022403002729,"contractQuantity":35,"contractRate":718,"securityName":"Multipurpose Finance Company  Limited","sellerBrokerName":"Arun Securities (PVT) Ltd.","sellerMemberId":"3","stockId":471,"stockSymbol":"MPFL","tradeBookId":143345910,"tradeTime":"2025-02-24T11:42:44.136543"},{"businessDate":"2025-02-24","buyerBrokerName":"Sani Securities Company Ltd.","buyerMemberId":"42","contractAmount":72000,"contractId":2025022403002728,"contractQuantity":100,"contractRate":720,"securityName":"Multipurpose Finance Company  Limited","sellerBrokerName":"Arun Securities (PVT) Ltd.","sellerMemberId":"3","stockId":471,"stockSymbol":"MPFL","tradeBookId":143345908,"tradeTime":"2025-02-24T11:42:44.136498"},{"businessDate":"2025-02-24","buyerBrokerName":"Premier Securities Company Ltd.","buyerMemberId":"32","contractAmount":21687,"contractId":2025022403002402,"contractQuantity":30,"contractRate":722.9,"securityName":"Multipurpose Finance Company  Limited","sellerBrokerName":"ABC Securities Private Limited","sellerMemberId":"17","stockId":471,"stockSymbol":"MPFL","tradeBookId":143342270,"tradeTime":"2025-02-24T11:38:57.318722"},{"businessDate":"2025-02-24","buyerBrokerName":"J.F. Securites (PVT) Ltd.","buyerMemberId":"7","contractAmount":86748,"contractId":2025022403002356,"contractQuantity":120,"contractRate":722.9,"securityName":"Multipurpose Finance Company  Limited","sellerBrokerName":"ABC Securities Private Limited","sellerMemberId":"17","stockId":471,"stockSymbol":"MPFL","tradeBookId":143341802,"tradeTime":"2025-02-24T11:38:20.476743"},{"businessDate":"2025-02-24","buyerBrokerName":"J.F. Securites (PVT) Ltd.","buyerMemberId":"7","contractAmount":43200,"contractId":2025022403002355,"contractQuantity":60,"contractRate":720,"securityName":"Multipurpose Finance Company  Limited","sellerBrokerName":"Online Securities Pvt. Ltd.","sellerMemberId":"49","stockId":471,"stockSymbol":"MPFL","tradeBookId":143341799,"tradeTime":"2025-02-24T11:38:20.47669"},{"businessDate":"2025-02-24","buyerBrokerName":"J.F. Securites (PVT) Ltd.","buyerMemberId":"7","contractAmount":14400,"contractId":2025022403002354,"contractQuantity":20,"contractRate":720,"securityName":"Multipurpose Finance Company  Limited","sellerBrokerName":"Naasa Securities Co. Ltd.","sellerMemberId":"58","stockId":471,"stockSymbol":"MPFL","tradeBookId":143341797,"tradeTime":"2025-02-24T11:38:20.47658"},{"businessDate":"2025-02-24","buyerBrokerName":"Sani Securities Company Ltd.","buyerMemberId":"42","contractAmount":143600,"contractId":2025022403001048,"contractQuantity":200,"contractRate":718,"securityName":"Multipurpose Finance Company  Limited","sellerBrokerName":"Premier Securities Company Ltd.","sellerMemberId":"32","stockId":471,"stockSymbol":"MPFL","tradeBookId":143325230,"tradeTime":"2025-02-24T11:20:42.398095"},{"businessDate":"2025-02-24","buyerBrokerName":"Investment Management Nepal Pvt. Ltd.","buyerMemberId":"53","contractAmount":267900,"contractId":2025022403000994,"contractQuantity":375,"contractRate":714.4,"securityName":"Multipurpose Finance Company  Limited","sellerBrokerName":"Midas Stock Broking Company Private Limited","sellerMemberId":"21","stockId":471,"stockSymbol":"MPFL","tradeBookId":143324267,"tradeTime":"2025-02-24T11:19:38.0983"},{"businessDate":"2025-02-24","buyerBrokerName":"Premier Securities Company Ltd.","buyerMemberId":"32","contractAmount":89325,"contractId":2025022403000993,"contractQuantity":125,"contractRate":714.6,"securityName":"Multipurpose Finance Company  Limited","sellerBrokerName":"Midas Stock Broking Company Private Limited","sellerMemberId":"21","stockId":471,"stockSymbol":"MPFL","tradeBookId":143324266,"tradeTime":"2025-02-24T11:19:38.098137"},{"businessDate":"2025-02-24","buyerBrokerName":"Premier Securities Company Ltd.","buyerMemberId":"32","contractAmount":21432,"contractId":2025022403000739,"contractQuantity":30,"contractRate":714.4,"securityName":"Multipurpose Finance Company  Limited","sellerBrokerName":"Siprabi Securities Pvt. Ltd.","sellerMemberId":"22","stockId":471,"stockSymbol":"MPFL","tradeBookId":143320979,"tradeTime":"2025-02-24T11:15:48.342587"},{"businessDate":"2025-02-24","buyerBrokerName":"Investment Management Nepal Pvt. Ltd.","buyerMemberId":"53","contractAmount":356750,"contractId":2025022403000392,"contractQuantity":500,"contractRate":713.5,"securityName":"Multipurpose Finance Company  Limited","sellerBrokerName":"Midas Stock Broking Company Private Limited","sellerMemberId":"21","stockId":471,"stockSymbol":"MPFL","tradeBookId":143316075,"tradeTime":"2025-02-24T11:09:20.260761"},{"businessDate":"2025-02-24","buyerBrokerName":"Dipshikha Dhitopatra Karobar Co. Pvt Ltd.","buyerMemberId":"38","contractAmount":12138,"contractId":2025022403000307,"contractQuantity":17,"contractRate":714,"securityName":"Multipurpose Finance Company  Limited","sellerBrokerName":"ABC Securities Private Limited","sellerMemberId":"17","stockId":471,"stockSymbol":"MPFL","tradeBookId":143314955,"tradeTime":"2025-02-24T11:07:57.687651"},{"businessDate":"2025-02-24","buyerBrokerName":"Kohinoor Investment \u0026 Securities Pvt. Ltd.","buyerMemberId":"35","contractAmount":7260,"contractId":2025022403000014,"contractQuantity":10,"contractRate":726,"securityName":"Multipurpose Finance Company  Limited","sellerBrokerName":"Sumeru Securities Pvt. Ltd.","sellerMemberId":"39","stockId":471,"stockSymbol":"MPFL","tradeBookId":143309843,"tradeTime":"2025-02-24T10:46:00.044456"}],"date":"2025-02-24","totalAmount":17187700.6,"totalQty":24207,"totalTrades":194}